skill_date_time/LICENSE
skill_date_time/LICENSE.md
skill_date_time/README.md
skill_date_time/__init__.py
skill_date_time/skill.json
skill_date_time/version.py
skill_date_time/locale/ca-es/timezone.value
skill_date_time/locale/ca-es/what.time.is.it.intent
skill_date_time/locale/ca-es/dialog/date.dialog
skill_date_time/locale/ca-es/dialog/time.current.dialog
skill_date_time/locale/ca-es/dialog/time.tz.not.found.dialog
skill_date_time/locale/ca-es/regex/location.rx
skill_date_time/locale/ca-es/vocab/Date.voc
skill_date_time/locale/ca-es/vocab/Query.voc
skill_date_time/locale/ca-es/vocab/Time.voc
skill_date_time/locale/da-dk/timezone.value
skill_date_time/locale/da-dk/what.time.is.it.intent
skill_date_time/locale/da-dk/dialog/date.dialog
skill_date_time/locale/da-dk/dialog/time.current.dialog
skill_date_time/locale/da-dk/dialog/time.tz.not.found.dialog
skill_date_time/locale/da-dk/regex/location.rx
skill_date_time/locale/da-dk/vocab/Date.voc
skill_date_time/locale/da-dk/vocab/Query.voc
skill_date_time/locale/da-dk/vocab/Time.voc
skill_date_time/locale/de-de/timezone.value
skill_date_time/locale/de-de/what.time.is.it.intent
skill_date_time/locale/de-de/dialog/date.dialog
skill_date_time/locale/de-de/dialog/time.current.dialog
skill_date_time/locale/de-de/dialog/time.tz.not.found.dialog
skill_date_time/locale/de-de/regex/location.rx
skill_date_time/locale/de-de/vocab/Date.voc
skill_date_time/locale/de-de/vocab/Time.voc
skill_date_time/locale/en-us/timezone.value
skill_date_time/locale/en-us/dialog/date.dialog
skill_date_time/locale/en-us/dialog/date_time_in_location.dialog
skill_date_time/locale/en-us/dialog/time.current.dialog
skill_date_time/locale/en-us/dialog/time.tz.not.found.dialog
skill_date_time/locale/en-us/dialog/word_friday.dialog
skill_date_time/locale/en-us/dialog/word_monday.dialog
skill_date_time/locale/en-us/dialog/word_saturday.dialog
skill_date_time/locale/en-us/dialog/word_sunday.dialog
skill_date_time/locale/en-us/dialog/word_thursday.dialog
skill_date_time/neon_skill_date_time.egg-info/PKG-INFO
skill_date_time/neon_skill_date_time.egg-info/SOURCES.txt
skill_date_time/neon_skill_date_time.egg-info/dependency_links.txt
skill_date_time/neon_skill_date_time.egg-info/entry_points.txt
skill_date_time/neon_skill_date_time.egg-info/requires.txt
skill_date_time/neon_skill_date_time.egg-info/top_level.txt
neon_skill_date_time-1.1.1.dist-info/LICENSE
neon_skill_date_time-1.1.1.dist-info/LICENSE.md
neon_skill_date_time-1.1.1.dist-info/METADATA
neon_skill_date_time-1.1.1.dist-info/WHEEL
neon_skill_date_time-1.1.1.dist-info/entry_points.txt
neon_skill_date_time-1.1.1.dist-info/top_level.txt
neon_skill_date_time-1.1.1.dist-info/RECORD
