Metadata-Version: 2.1
Name: neon-skill-date-time
Version: 1.1.1
Home-page: https://github.com/NeonGeckoCom/skill-date_time
Author: Neongecko
Author-email: developers@neon.ai
License: BSD-3-Clause
License-File: LICENSE
License-File: LICENSE.md
Requires-Dist: pytz>=2022.1
Requires-Dist: geocoder~=1.38
Requires-Dist: timezonefinder~=5.2
Requires-Dist: ovos-bus-client>=0.0.4,~=0.0
Requires-Dist: ovos-utils>=0.0.34,~=0.0
Requires-Dist: neon-utils~=1.12
Requires-Dist: ovos-workshop>=0.0.12,~=0.0
Requires-Dist: ovos-lingua-franca~=0.4
Provides-Extra: test
Requires-Dist: neon-minerva[padatious]~=0.3; extra == "test"
Requires-Dist: ovos-lingua-franca>=0.4.8a3; extra == "test"
